dirindex/__init__.py
dirindex/_cli.py
dirindex/version.py
dirindex/templates/apache
dirindex/templates/golang
dirindex/templates/lighttpd
dirindex/templates/ls-l
dirindex/templates/nginx
dirindex/templates/nginx-noexact
dirindex/templates/python
dirindex/templates/thttpd
dirindex/templates/tomcat
dirindex/templates/webrick
dirindex-0.4.dist-info/LICENSE
dirindex-0.4.dist-info/METADATA
dirindex-0.4.dist-info/WHEEL
dirindex-0.4.dist-info/entry_points.txt
dirindex-0.4.dist-info/top_level.txt
dirindex-0.4.dist-info/RECORD
