Metadata-Version: 2.1
Name: dirindex
Version: 0.4
Summary: make index.html
Home-page: https://github.com/wtnb75/dirindex
Author: Watanabe Takashi
Author-email: wtnb75@gmail.com
License: MIT
Platform: UNKNOWN
Classifier: Development Status :: 3 - Alpha
Classifier: Intended Audience :: Developers
Classifier: License :: OSI Approved :: MIT License
Classifier: Programming Language :: Python :: 3
Requires-Dist: Click
Requires-Dist: Jinja2
